autotrain_llm/__init__.py
autotrain_llm/utils.py
autotrain_llm/cli/__init__.py
autotrain_llm/cli/cli.py
autotrain_llm/cli/run_ui.py
autotrain_llm/deploy/__init__.py
autotrain_llm/infer/__init__.py
autotrain_llm/trainer/__init__.py
autotrain_llm/trainer/callbacks.py
autotrain_llm/trainer/clm.py
autotrain_llm/trainer/dataset.py
autotrain_llm/trainer/mlm.py
autotrain_llm/trainer/utils.py
autotrain_llm/ui/__init__.py
autotrain_llm/ui/app.py
autotrain_llm-0.2.0.dist-info/LICENSE
autotrain_llm-0.2.0.dist-info/METADATA
autotrain_llm-0.2.0.dist-info/WHEEL
autotrain_llm-0.2.0.dist-info/entry_points.txt
autotrain_llm-0.2.0.dist-info/top_level.txt
autotrain_llm-0.2.0.dist-info/RECORD
